LICENSE
LICENSE.txt
MANIFEST.in
README
README.md
requirements.txt
setup.cfg
setup.py
pythaiaddr/__init__.py
pythaiaddr.egg-info/PKG-INFO
pythaiaddr.egg-info/SOURCES.txt
pythaiaddr.egg-info/dependency_links.txt
pythaiaddr.egg-info/requires.txt
pythaiaddr.egg-info/top_level.txt
pythaiaddr/corpus/Thai_addr_bigrame_frequency.txt
pythaiaddr/corpus/Thai_addr_trigrame_frequency.txt
pythaiaddr/corpus/Thai_addr_unigrame_frequency.txt
pythaiaddr/corpus/Thai_addr_word_frequency.txt
pythaiaddr/corpus/Thai_address.txt
pythaiaddr/corpus/Thai_address_indication.txt
pythaiaddr/corpus/Thai_address_with_BKKraod.txt
pythaiaddr/corpus/__init__.py
pythaiaddr/corpus/core.py
pythaiaddr/corpus/corpus.py
pythaiaddr/corpus/posibel_address.csv
pythaiaddr/corpus/posible_address.txt
pythaiaddr/corpus/posible_address_original.txt
pythaiaddr/corpus/preprocess.py
pythaiaddr/spell/__init__.py
pythaiaddr/spell/core.py
pythaiaddr/spell/ediz.py
pythaiaddr/spell/norvig.py
pythaiaddr/spell/symspell.py
pythaiaddr/tokenize/__init__.py
pythaiaddr/tokenize/newmm.py
pythaiaddr/tokenize/tcc.py
pythaiaddr/tokenize/tokenizer.py
pythaiaddr/util/trie.py